moffragmentor/Systre-19.6.0.jar
moffragmentor/__init__.py
moffragmentor/mof.py
moffragmentor/net.py
moffragmentor/systre.license
moffragmentor/version.py
moffragmentor/cli/__init__.py
moffragmentor/descriptors/__init__.py
moffragmentor/descriptors/sbu_dimensionality.py
moffragmentor/fragmentor/__init__.py
moffragmentor/fragmentor/_graphsearch.py
moffragmentor/fragmentor/_no_core_linker.py
moffragmentor/fragmentor/branching_points.py
moffragmentor/fragmentor/filter.py
moffragmentor/fragmentor/linkerlocator.py
moffragmentor/fragmentor/molfromgraph.py
moffragmentor/fragmentor/nodelocator.py
moffragmentor/fragmentor/solventlocator.py
moffragmentor/fragmentor/splitter.py
moffragmentor/harvester/__init__.py
moffragmentor/harvester/harvest_building_blocks.py
moffragmentor/molecule/__init__.py
moffragmentor/molecule/nonsbumolecule.py
moffragmentor/molecule/nonsbumoleculecollection.py
moffragmentor/sbu/__init__.py
moffragmentor/sbu/linker.py
moffragmentor/sbu/linkercollection.py
moffragmentor/sbu/node.py
moffragmentor/sbu/nodecollection.py
moffragmentor/sbu/sbu.py
moffragmentor/sbu/sbucollection.py
moffragmentor/utils/__init__.py
moffragmentor/utils/errors.py
moffragmentor/utils/mol_compare.py
moffragmentor/utils/periodic_graph.py
moffragmentor/utils/systre.py
moffragmentor-0.0.6.dist-info/LICENSE
moffragmentor-0.0.6.dist-info/METADATA
moffragmentor-0.0.6.dist-info/WHEEL
moffragmentor-0.0.6.dist-info/entry_points.txt
moffragmentor-0.0.6.dist-info/top_level.txt
moffragmentor-0.0.6.dist-info/RECORD
