Metadata-Version: 2.1
Name: moffragmentor
Version: 0.0.6
Summary: Splits MOFs into metal nodes and linkers.
Home-page: https://github.com/kjappelbaum/moffragmentor
Download-URL: https://github.com/kjappelbaum/moffragmentor/releases
Author: Kevin Maik Jablonka
Author-email: mail@kjablonka.com
Maintainer-email: mail@kjablonka.com
License: MIT
Project-URL: Bug Tracker, https://github.com/kjappelbaum/moffragmentor/issues
Project-URL: Source Code, https://github.com/kjappelbaum/moffragmentor/
Keywords: mof,chemistry,materials-science,reticular-chemistry,SBU,topology,net,fragmentation,building-blocks
Classifier: Development Status :: 1 - Planning
Classifier: Environment :: Console
Classifier: Intended Audience :: Developers
Classifier: License :: OSI Approved :: MIT License
Classifier: Operating System :: OS Independent
Classifier: Framework :: Pytest
Classifier: Framework :: tox
Classifier: Framework :: Sphinx
Classifier: Programming Language :: Python
Classifier: Programming Language :: Python :: 3.8
Classifier: Programming Language :: Python :: 3.9
Classifier: Programming Language :: Python :: 3.10
Classifier: Programming Language :: Python :: 3 :: Only
Requires-Python: >=3.8
License-File: LICENSE
Requires-Dist: pymatgen
Requires-Dist: click
Requires-Dist: backports.cached-property
Requires-Dist: networkx
Requires-Dist: pyyaml
Requires-Dist: timeout-decorator
Requires-Dist: joblib
Requires-Dist: loguru
Requires-Dist: ase
Requires-Dist: nglview
Requires-Dist: rdkit
Requires-Dist: scikit-spatial
Requires-Dist: pubchempy
Requires-Dist: more-itertools
Requires-Dist: structuregraph-helpers
Provides-Extra: docs
Requires-Dist: sphinx ; extra == 'docs'
Requires-Dist: furo ; extra == 'docs'
Requires-Dist: sphinx-click ; extra == 'docs'
Requires-Dist: sphinx-autodoc-typehints ; extra == 'docs'
Requires-Dist: sphinx-automodapi ; extra == 'docs'
Requires-Dist: sphinx-copybutton ; extra == 'docs'
Provides-Extra: lint
Requires-Dist: isort ; extra == 'lint'
Requires-Dist: black ; extra == 'lint'
Requires-Dist: flake8 ; extra == 'lint'
Requires-Dist: bumpversion ; extra == 'lint'
Provides-Extra: pubchem
Requires-Dist: pubchempy ; extra == 'pubchem'
Provides-Extra: tests
Requires-Dist: pytest ; extra == 'tests'
Requires-Dist: tox ; extra == 'tests'
Requires-Dist: coverage ; extra == 'tests'
Requires-Dist: pytest-xdist ; extra == 'tests'
